torch_tps/__init__.py
torch_tps/polynomial_transform.py
torch_tps/py.typed
torch_tps/thin_plate_spline.py
torch_tps-1.2.1.dist-info/licenses/LICENSE
torch_tps-1.2.1.dist-info/WHEEL
torch_tps-1.2.1.dist-info/METADATA
torch_tps-1.2.1.dist-info/RECORD
